clip_values/__init__.py
clip_values-1.0.dist-info/LICENSE
clip_values-1.0.dist-info/METADATA
clip_values-1.0.dist-info/WHEEL
clip_values-1.0.dist-info/top_level.txt
clip_values-1.0.dist-info/RECORD
