Metadata-Version: 2.1
Name: clip-values
Version: 1.0
Summary: Clipping values in a human-readable way.
Home-page: https://github.com/RojerGS/clip_values
Author: Rodrigo Girão Serrão
Author-email: rodrigo@mathspp.com
License: UNKNOWN
Project-URL: Bug Tracker, https://github.com/RojerGS/clip_values/issues
Platform: UNKNOWN
Classifier: Programming Language :: Python :: 3
Classifier: License :: OSI Approved :: MIT License
Classifier: Operating System :: OS Independent
Requires-Python: >=3
